autosubmit_api/__init__.py
autosubmit_api/app.py
autosubmit_api/cli.py
autosubmit_api/logger.py
autosubmit_api/middleware.py
autosubmit_api/auth/__init__.py
autosubmit_api/auth/oidc.py
autosubmit_api/auth/utils.py
autosubmit_api/autosubmit_legacy/__init__.py
autosubmit_api/autosubmit_legacy/job/__init__.py
autosubmit_api/autosubmit_legacy/job/job_list.py
autosubmit_api/autosubmit_legacy/job/job_utils.py
autosubmit_api/bgtasks/__init__.py
autosubmit_api/bgtasks/bgtask.py
autosubmit_api/bgtasks/scheduler.py
autosubmit_api/bgtasks/tasks/__init__.py
autosubmit_api/bgtasks/tasks/details_updater.py
autosubmit_api/bgtasks/tasks/status_updater.py
autosubmit_api/builders/__init__.py
autosubmit_api/builders/basic_builder.py
autosubmit_api/builders/configuration_facade_builder.py
autosubmit_api/builders/experiment_builder.py
autosubmit_api/builders/experiment_history_builder.py
autosubmit_api/builders/joblist_helper_builder.py
autosubmit_api/builders/joblist_loader_builder.py
autosubmit_api/common/__init__.py
autosubmit_api/common/utils.py
autosubmit_api/common/utils_for_testing.py
autosubmit_api/components/__init__.py
autosubmit_api/components/experiment/__init__.py
autosubmit_api/components/experiment/configuration_facade.py
autosubmit_api/components/experiment/file_metadata.py
autosubmit_api/components/experiment/pkl_organizer.py
autosubmit_api/components/jobs/__init__.py
autosubmit_api/components/jobs/job_factory.py
autosubmit_api/components/jobs/job_support.py
autosubmit_api/components/jobs/joblist_helper.py
autosubmit_api/components/jobs/joblist_loader.py
autosubmit_api/components/jobs/utils.py
autosubmit_api/components/representations/__init__.py
autosubmit_api/components/representations/graph/__init__.py
autosubmit_api/components/representations/graph/edge.py
autosubmit_api/components/representations/graph/graph.py
autosubmit_api/components/representations/tree/__init__.py
autosubmit_api/components/representations/tree/tree.py
autosubmit_api/config/IConfigStrategy.py
autosubmit_api-4.1.1.dist-info/licenses/LICENSE
autosubmit_api-4.1.1.dist-info/METADATA
autosubmit_api-4.1.1.dist-info/WHEEL
autosubmit_api-4.1.1.dist-info/entry_points.txt
autosubmit_api-4.1.1.dist-info/top_level.txt
autosubmit_api-4.1.1.dist-info/RECORD
