Metadata-Version: 2.4
Name: autosubmit_api
Version: 4.1.1
Summary: An extension to the Autosubmit package that serves its information as an API
Home-page: https://github.com/BSC-ES/autosubmit-api
Author: Luiggi Tenorio, Bruno P. Kinoshita, Cristian Gutiérrez, Julian Berlin, Wilmer Uruchi
Author-email: support-autosubmit@bsc.es
License: GNU GPL
Keywords: autosubmit,API
Classifier: Development Status :: 4 - Beta
Classifier: Intended Audience :: Developers
Classifier: License :: OSI Approved :: GNU General Public License v3 (GPLv3)
Classifier: Operating System :: POSIX :: Linux
Classifier: Programming Language :: Python :: 3.9
Requires-Python: >=3.9
License-File: LICENSE
Requires-Dist: fastapi[all]==0.115.0
Requires-Dist: pyjwt~=2.8.0
Requires-Dist: requests~=2.28.1
Requires-Dist: bscearth.utils~=0.5.2
Requires-Dist: pydotplus~=2.0.2
Requires-Dist: portalocker~=2.6.0
Requires-Dist: networkx<=2.6.3
Requires-Dist: scipy~=1.11.4
Requires-Dist: python-dotenv~=1.0.1
Requires-Dist: autosubmitconfigparser>=1.0.72
Requires-Dist: APScheduler~=3.10.4
Requires-Dist: gunicorn~=22.0.0
Requires-Dist: pydantic~=2.5.2
Requires-Dist: SQLAlchemy~=2.0.23
Requires-Dist: python-cas~=1.6.0
Requires-Dist: autosubmit==4.1.11
Provides-Extra: test
Requires-Dist: pytest; extra == "test"
Requires-Dist: pytest-cov; extra == "test"
Requires-Dist: pytest-asyncio; extra == "test"
Requires-Dist: ruff; extra == "test"
Provides-Extra: all
Requires-Dist: fastapi[all]==0.115.0; extra == "all"
Requires-Dist: pyjwt~=2.8.0; extra == "all"
Requires-Dist: requests~=2.28.1; extra == "all"
Requires-Dist: bscearth.utils~=0.5.2; extra == "all"
Requires-Dist: pydotplus~=2.0.2; extra == "all"
Requires-Dist: portalocker~=2.6.0; extra == "all"
Requires-Dist: networkx<=2.6.3; extra == "all"
Requires-Dist: scipy~=1.11.4; extra == "all"
Requires-Dist: python-dotenv~=1.0.1; extra == "all"
Requires-Dist: autosubmitconfigparser>=1.0.72; extra == "all"
Requires-Dist: APScheduler~=3.10.4; extra == "all"
Requires-Dist: gunicorn~=22.0.0; extra == "all"
Requires-Dist: pydantic~=2.5.2; extra == "all"
Requires-Dist: SQLAlchemy~=2.0.23; extra == "all"
Requires-Dist: python-cas~=1.6.0; extra == "all"
Requires-Dist: autosubmit==4.1.11; extra == "all"
Requires-Dist: pytest; extra == "all"
Requires-Dist: pytest-cov; extra == "all"
Requires-Dist: pytest-asyncio; extra == "all"
Requires-Dist: ruff; extra == "all"
Dynamic: author
Dynamic: author-email
Dynamic: classifier
Dynamic: description
Dynamic: description-content-type
Dynamic: home-page
Dynamic: keywords
Dynamic: license
Dynamic: license-file
Dynamic: provides-extra
Dynamic: requires-dist
Dynamic: requires-python
Dynamic: summary
